[{"img_path": "templates/0t.jpg", "p1": [48, 74], "p2": [195, 263], "comprimento": 147, "altura": 189}, {"img_path": "templates/1t.jpg", "p1": [226, 996], "p2": [1050, 1288], "comprimento": 824, "altura": 292}, {"img_path": "templates/2t.jpg", "p1": [94, 46], "p2": [367, 167], "comprimento": 273, "altura": 121}, {"img_path": "templates/3t.jpg", "p1": [314, 222], "p2": [1061, 685], "comprimento": 747, "altura": 463}, {"img_path": "templates/4t.jpg", "p1": [344, 25], "p2": [568, 118], "comprimento": 224, "altura": 93}, {"img_path": "templates/5t.jpg", "p1": [350, 96], "p2": [748, 831], "comprimento": 398, "altura": 735}, {"img_path": "templates/6t.jpg", "p1": [194, 407], "p2": [485, 728], "comprimento": 291, "altura": 321}, {"img_path": "templates/7t.jpg", "p1": [313, 429], "p2": [1155, 1241], "comprimento": 842, "altura": 812}, {"img_path": "templates/8t.jpg", "p1": [511, 17], "p2": [930, 186], "comprimento": 419, "altura": 169}, {"img_path": "templates/9t.jpg", "p1": [193, 49], "p2": [363, 181], "comprimento": 170, "altura": 132}, {"img_path": "templates/10t.jpg", "p1": [537, 563], "p2": [723, 732], "comprimento": 186, "altura": 169}, {"img_path": "templates/11t.jpg", "p1": [177, 47], "p2": [356, 350], "comprimento": 179, "altura": 303}, {"img_path": "templates/12t.jpg", "p1": [77, 62], "p2": [252, 234], "comprimento": 175, "altura": 172}, {"img_path": "templates/13t.jpg", "p1": [271, 366], "p2": [384, 600], "comprimento": 113, "altura": 234}, {"img_path": "templates/14t.jpg", "p1": [42, 383], "p2": [208, 559], "comprimento": 166, "altura": 176}, {"img_path": "templates/15t.jpg", "p1": [204, 244], "p2": [366, 322], "comprimento": 162, "altura": 78}, {"img_path": "templates/16t.jpg", "p1": [343, 17], "p2": [656, 150], "comprimento": 313, "altura": 133}, {"img_path": "templates/17t.jpg", "p1": [33, 420], "p2": [547, 589], "comprimento": 514, "altura": 169}, {"img_path": "templates/18t.jpg", "p1": [396, 38], "p2": [677, 134], "comprimento": 281, "altura": 96}, {"img_path": "templates/19t.jpg", "p1": [171, 161], "p2": [275, 318], "comprimento": 104, "altura": 157}, {"img_path": "templates/20t.jpg", "p1": [37, 348], "p2": [271, 432], "comprimento": 234, "altura": 84}, {"img_path": "templates/21t.jpg", "p1": [46, 264], "p2": [237, 325], "comprimento": 191, "altura": 61}, {"img_path": "templates/22t.jpg", "p1": [30, 274], "p2": [195, 338], "comprimento": 165, "altura": 64}, {"img_path": "templates/23t.jpg", "p1": [456, 168], "p2": [582, 255], "comprimento": 126, "altura": 87}, {"img_path": "templates/24t.jpg", "p1": [379, 38], "p2": [492, 266], "comprimento": 113, "altura": 228}, {"img_path": "templates/25t.jpg", "p1": [339, 339], "p2": [487, 446], "comprimento": 148, "altura": 107}, {"img_path": "templates/26t.jpg", "p1": [131, 343], "p2": [407, 470], "comprimento": 276, "altura": 127}, {"img_path": "templates/27t.jpg", "p1": [339, 27], "p2": [613, 184], "comprimento": 274, "altura": 157}, {"img_path": "templates/28t.jpg", "p1": [317, 83], "p2": [416, 203], "comprimento": 99, "altura": 120}, {"img_path": "templates/29t.jpg", "p1": [22, 347], "p2": [298, 428], "comprimento": 276, "altura": 81}, {"img_path": "templates/30t.jpg", "p1": [64, 33], "p2": [323, 168], "comprimento": 259, "altura": 135}, {"img_path": "templates/31t.jpg", "p1": [362, 350], "p2": [513, 448], "comprimento": 151, "altura": 98}, {"img_path": "templates/32t.jpg", "p1": [7, 266], "p2": [246, 376], "comprimento": 239, "altura": 110}, {"img_path": "templates/33t.jpg", "p1": [94, 451], "p2": [231, 598], "comprimento": 137, "altura": 147}, {"img_path": "templates/34t.jpg", "p1": [459, 183], "p2": [785, 559], "comprimento": 326, "altura": 376}, {"img_path": "templates/35t.jpg", "p1": [106, 382], "p2": [287, 539], "comprimento": 181, "altura": 157}, {"img_path": "templates/36t.jpg", "p1": [75, 244], "p2": [186, 347], "comprimento": 111, "altura": 103}, {"img_path": "templates/37t.jpg", "p1": [502, 289], "p2": [684, 517], "comprimento": 182, "altura": 228}, {"img_path": "templates/38t.jpg", "p1": [149, 367], "p2": [287, 451], "comprimento": 138, "altura": 84}, {"img_path": "templates/39t.jpg", "p1": [310, 21], "p2": [530, 351], "comprimento": 220, "altura": 330}, {"img_path": "templates/40t.jpg", "p1": [494, 45], "p2": [722, 207], "comprimento": 228, "altura": 162}, {"img_path": "templates/41t.jpg", "p1": [287, 823], "p2": [831, 1425], "comprimento": 544, "altura": 602}, {"img_path": "templates/42t.jpg", "p1": [17, 23], "p2": [583, 477], "comprimento": 566, "altura": 454}, {"img_path": "templates/43t.jpg", "p1": [62, 335], "p2": [216, 396], "comprimento": 154, "altura": 61}, {"img_path": "templates/44t.jpg", "p1": [58, 113], "p2": [311, 377], "comprimento": 253, "altura": 264}, {"img_path": "templates/45t.jpg", "p1": [339, 1041], "p2": [785, 1217], "comprimento": 446, "altura": 176}, {"img_path": "templates/46t.jpg", "p1": [847, 55], "p2": [1709, 535], "comprimento": 862, "altura": 480}]